xfyunsdkspeech/__init__.py
xfyunsdkspeech/iat_client.py
xfyunsdkspeech/igr_client.py
xfyunsdkspeech/ise_client.py
xfyunsdkspeech/lfasr_client.py
xfyunsdkspeech/qbh_client.py
xfyunsdkspeech/rtasr_client.py
xfyunsdkspeech/tts_client.py
xfyunsdkspeech-0.0.4.dist-info/LICENSE
xfyunsdkspeech-0.0.4.dist-info/METADATA
xfyunsdkspeech-0.0.4.dist-info/WHEEL
xfyunsdkspeech-0.0.4.dist-info/top_level.txt
xfyunsdkspeech-0.0.4.dist-info/RECORD
