Metadata-Version: 2.1
Name: xfyunsdkspeech
Version: 0.0.4
Summary: a sdk speech for xfyun
Author: zyding6
Author-email: zyding6@iflytek.com
Requires-Python: >=3.7.1
License-File: LICENSE
Requires-Dist: xfyunsdkcore >=0.0.3
Requires-Dist: python-dotenv
Provides-Extra: test
Requires-Dist: pytest >=6.0 ; extra == 'test'
Requires-Dist: pytest-asyncio >=0.21.0 ; extra == 'test'
Requires-Dist: pytest-cov ; extra == 'test'
